astrocats/__init__.py
astrocats/__main__.py
astrocats/main.py
astrocats/catalog/__init__.py
astrocats/catalog/__main__.py
astrocats/catalog/analysis.py
astrocats/catalog/argshandler.py
astrocats/catalog/catalog.py
astrocats/catalog/catdict.py
astrocats/catalog/entry.py
astrocats/catalog/error.py
astrocats/catalog/key.py
astrocats/catalog/main.py
astrocats/catalog/model.py
astrocats/catalog/photometry.py
astrocats/catalog/quantity.py
astrocats/catalog/realization.py
astrocats/catalog/source.py
astrocats/catalog/spectrum.py
astrocats/catalog/task.py
astrocats/catalog/tasks/__init__.py
astrocats/catalog/tasks/merge_duplicates.py
astrocats/catalog/tasks/sanitize.py
astrocats/catalog/tasks/set_preferred_names.py
astrocats/catalog/tasks/test.py
astrocats/catalog/utils/__init__.py
astrocats/catalog/utils/dates.py
astrocats/catalog/utils/digits.py
astrocats/catalog/utils/imports.py
astrocats/catalog/utils/logger.py
astrocats/catalog/utils/plotting.py
astrocats/catalog/utils/sorting.py
astrocats/catalog/utils/strings.py
astrocats/catalog/utils/tq_funcs.py
astrocats-0.3.3.dist-info/DESCRIPTION.rst
astrocats-0.3.3.dist-info/METADATA
astrocats-0.3.3.dist-info/RECORD
astrocats-0.3.3.dist-info/WHEEL
astrocats-0.3.3.dist-info/metadata.json
astrocats-0.3.3.dist-info/top_level.txt
