Metadata-Version: 2.0
Name: astrocats
Version: 0.3.3
Summary: Package for downloading, analyzing, and constructing open astronomy catalogs.
Home-page: https://github.com/astrocatalogs/astrocats
Author: James Guillochon
Author-email: guillochon@gmail.com
License: MIT
Download-URL: https://github.com/astrocatalogs/astrocats/tarball/0.3.3
Keywords: astronomy
Platform: UNKNOWN
Classifier: Development Status :: 3 - Alpha
Classifier: License :: OSI Approved :: MIT License
Classifier: Programming Language :: Python :: 3.5
Requires-Dist: GitPython (>=2.0.6)
Requires-Dist: ads (>=0.11.3)
Requires-Dist: argparse (>=1.1.0)
Requires-Dist: astropy (>=1.2.1)
Requires-Dist: astroquery (>=0.3.2)
Requires-Dist: beautifulsoup4 (>=4.4.1)
Requires-Dist: bokeh (>=0.12.0)
Requires-Dist: future (>=0.16.0)
Requires-Dist: inflect (>=0.2.5)
Requires-Dist: m3-cdecimal (>=2.3)
Requires-Dist: palettable (>=2.1.1)
Requires-Dist: psutil (>=4.3.0)
Requires-Dist: seaborn (>=0.7.1)
Requires-Dist: tqdm (>=4.5.0)
Requires-Dist: tweepy (>=3.5.0)
